setup.py
NaBiAPPPPPPPPPPPPPPPP/__init__.py
NaBiAPPPPPPPPPPPPPPPP/cFunction.py
NaBiAPPPPPPPPPPPPPPPP.egg-info/PKG-INFO
NaBiAPPPPPPPPPPPPPPPP.egg-info/SOURCES.txt
NaBiAPPPPPPPPPPPPPPPP.egg-info/dependency_links.txt
NaBiAPPPPPPPPPPPPPPPP.egg-info/top_level.txt