Metadata-Version: 2.1
Name: NaBiAPPPPPPPPPPPPPPPP
Version: 0.0.1
Summary: isoweek calculation and so on
Home-page: http://github.com/kimhyokwan/hklabhklab
Author: kimhyokwan
Author-email: haiteam@kopo.ac.kr
License: MIT
Keywords: calendar,isoweek,listsum
